rtd_phylogeny.py
rtd_phylogeny-0.0.51.dist-info/LICENSE
rtd_phylogeny-0.0.51.dist-info/METADATA
rtd_phylogeny-0.0.51.dist-info/WHEEL
rtd_phylogeny-0.0.51.dist-info/top_level.txt
rtd_phylogeny-0.0.51.dist-info/RECORD
