Metadata-Version: 2.1
Name: rtd-phylogeny
Version: 0.0.51
Summary: Molecular phylogeny analysis using Return time distribution (RTD) based alignment-free sequence analysis method
Home-page: https://github.com/pandurang-kolekar/rtd-phylogeny
Author: Pandurang Kolekar
Author-email: pandurang.kolekar@gmail.com
License: UNKNOWN
Platform: UNKNOWN
Classifier: Programming Language :: Python :: 3.7
Classifier: Operating System :: OS Independent
Classifier: License :: OSI Approved :: MIT License
Requires-Python: >=3.7
Requires-Dist: biopython (>=1.77)
Requires-Dist: DendroPy (>=4.4.0)
Requires-Dist: ete3 (>=3.1.1)
Requires-Dist: matplotlib (>=3.3.0)
Requires-Dist: numpy (>=1.18.5)
Requires-Dist: pandas (>=1.0.5)
Requires-Dist: scipy (>=1.5.1)
